pytrnsys_process/__init__.py
pytrnsys_process/py.typed
pytrnsys_process/api/__init__.py
pytrnsys_process/config/__init__.py
pytrnsys_process/config/constants.py
pytrnsys_process/config/settings.py
pytrnsys_process/deck/__init__.py
pytrnsys_process/deck/ddck.lark
pytrnsys_process/deck/extractor.py
pytrnsys_process/deck/parser.py
pytrnsys_process/deck/visitor_helpers.py
pytrnsys_process/log/__init__.py
pytrnsys_process/log/logger.py
pytrnsys_process/plot/__init__.py
pytrnsys_process/plot/plot_wrappers.py
pytrnsys_process/plot/plotters.py
pytrnsys_process/process/__init__.py
pytrnsys_process/process/data_structures.py
pytrnsys_process/process/file_type_detector.py
pytrnsys_process/process/process_batch.py
pytrnsys_process/process/process_sim.py
pytrnsys_process/read/__init__.py
pytrnsys_process/read/readers.py
pytrnsys_process/util/__init__.py
pytrnsys_process/util/file_converter.py
pytrnsys_process/util/utils.py
pytrnsys_process-0.0.29.dist-info/licenses/LICENSE
pytrnsys_process-0.0.29.dist-info/METADATA
pytrnsys_process-0.0.29.dist-info/WHEEL
pytrnsys_process-0.0.29.dist-info/top_level.txt
pytrnsys_process-0.0.29.dist-info/RECORD
