Metadata-Version: 2.4
Name: pytrnsys_process
Version: 0.0.29
Summary: Post processing for pytrnsys
Author-email: Alex Hobé <alex.hobe@ost.ch>, Sebastian Swoboda <sebastian@swoboda.ch>, Damian Birchler <damian.birchler@ost.ch>
License-Expression: GPL-3.0-or-later
Project-URL: Homepage, https://github.com/SPF-OST/pytrnsys_process
Project-URL: Issues, https://github.com/SPF-OST/pytrnsys_process/issues
Project-URL: Documentation, https://pytrnsys-process.readthedocs.io
Classifier: Programming Language :: Python :: 3
Classifier: Operating System :: OS Independent
Requires-Python: >=3.12
License-File: LICENSE
Requires-Dist: pandas
Requires-Dist: pyarrow
Requires-Dist: matplotlib
Requires-Dist: lark
Dynamic: license-file
